{
    "AX": {
        "error": 0.004704501169170873, 
        "error_type": "SEM", 
        "filter_outliers_dict": {
            "filter_outliers": true, 
            "iterations": 1, 
            "std_devs": 2
        }, 
        "fit": "average", 
        "value": -0.11756714916504209
    }, 
    "H1": {
        "error": 0.00684262844016404, 
        "error_type": "SEM", 
        "filter_outliers_dict": {
            "filter_outliers": true, 
            "iterations": 1, 
            "std_devs": 2
        }, 
        "fit": "average", 
        "value": -0.05459567427953173
    }, 
    "H2": {
        "error": 0.016107244143842032, 
        "error_type": "SEM", 
        "filter_outliers_dict": {
            "filter_outliers": true, 
            "iterations": 1, 
            "std_devs": 2
        }, 
        "fit": "average", 
        "value": -0.6677946502602956
    }, 
    "L1": {
        "error": 0.01673626618683963, 
        "error_type": "SEM", 
        "filter_outliers_dict": {
            "filter_outliers": true, 
            "iterations": 1, 
            "std_devs": 2
        }, 
        "fit": "average", 
        "value": -0.26625405370485405
    }, 
    "L2(CDD)": {
        "error": 0.0, 
        "error_type": "SEM", 
        "filter_outliers_dict": {
            "filter_outliers": true, 
            "iterations": 1, 
            "std_devs": 2
        }, 
        "fit": "average", 
        "value": 0.0
    }
}