{
    "Ar36": {
        "error": 0.004856390295750542,
        "error_type": "SEM",
        "filter_outliers_dict": {
            "filter_outliers": true,
            "iterations": 2,
            "std_devs": 2
        },
        "fit": "Parabolic",
        "value": 3.8041854374082544
    },
    "Ar37": {
        "error": 0.01356614099594377,
        "error_type": "SEM",
        "filter_outliers_dict": {
            "filter_outliers": true,
            "iterations": 2,
            "std_devs": 2
        },
        "fit": "linear",
        "value": 8.979743612813337
    },
    "Ar38": {
        "error": 0.004994766212848353,
        "error_type": "SEM",
        "filter_outliers_dict": {
            "filter_outliers": true,
            "iterations": 2,
            "std_devs": 2
        },
        "fit": "linear",
        "value": 1.0996586101047983
    },
    "Ar39": {
        "error": 0.01360374984062077,
        "error_type": "SEM",
        "filter_outliers_dict": {
            "filter_outliers": true,
            "iterations": 2,
            "std_devs": 2
        },
        "fit": "Parabolic",
        "value": 13.210803718341637
    },
    "Ar40": {
        "error": 0.08923730417375009,
        "error_type": "SEM",
        "filter_outliers_dict": {
            "filter_outliers": true,
            "iterations": 2,
            "std_devs": 2
        },
        "fit": "Parabolic",
        "value": 1174.7580638038758
    }
}